qd2_node/__init__.py
qd2_node/functions.py
qd2_node/http_receptor.py
qd2_node/receive_qd2.py
qd2_node-2.1.1.dist-info/METADATA
qd2_node-2.1.1.dist-info/WHEEL
qd2_node-2.1.1.dist-info/RECORD
