Metadata-Version: 2.4
Name: qd2_node
Version: 2.1.1
Summary: Software for Quditto node
Author-email: Javier Perez <javier.perez@imdea.org>, Blanca Lopez <blanca.lopez@imdea.org>, Angela Diaz <angela.diaz@imdea.org>
Requires-Python: >=3.8
Requires-Dist: aio-pika~=9.5.5
Requires-Dist: fastapi~=0.115.11
Requires-Dist: pika~=1.3.2
Requires-Dist: uvicorn~=0.34.0
